jsCalc/app.py
jsCalc1023-0.0.1.dist-info/LICENSE
jsCalc1023-0.0.1.dist-info/METADATA
jsCalc1023-0.0.1.dist-info/WHEEL
jsCalc1023-0.0.1.dist-info/top_level.txt
jsCalc1023-0.0.1.dist-info/RECORD
