Metadata-Version: 2.1
Name: jsCalc1023
Version: 0.0.1
Summary: oss-dev my calculator
Author: junsu bae
Author-email: hashilyze@gmail.com
Classifier: Programming Language :: Python :: 3.10
License-File: LICENSE
